pokemonPalette/__ini__.py
pokemonPalette/__main__.py
pokemonPalette/pokePalette.py
pokemonPalette-0.0.2.3.dist-info/LICENSE
pokemonPalette-0.0.2.3.dist-info/METADATA
pokemonPalette-0.0.2.3.dist-info/WHEEL
pokemonPalette-0.0.2.3.dist-info/top_level.txt
pokemonPalette-0.0.2.3.dist-info/RECORD
