Metadata-Version: 2.1
Name: pokemonPalette
Version: 0.0.2.3
Summary: The pokemonPalette is a python library generate a color palette based on the colors of a chosen pokemon.
Home-page: https://github.com/MilanCalegari/pokemonPalette
Author: Rodrigo M Calegari
Author-email: rodrigomcalegari@gmail.com
License: MIT
Platform: UNKNOWN
Classifier: Programming Language :: Python :: 3
License-File: LICENSE
